kameleo/__init__.py
kameleo/local_api_client/__init__.py
kameleo/local_api_client/api_client.py
kameleo/local_api_client/api_response.py
kameleo/local_api_client/configuration.py
kameleo/local_api_client/exceptions.py
kameleo/local_api_client/kameleo_local_api_client.py
kameleo/local_api_client/py.typed
kameleo/local_api_client/rest.py
kameleo/local_api_client/api/__init__.py
kameleo/local_api_client/api/cookie_api.py
kameleo/local_api_client/api/fingerprint_api.py
kameleo/local_api_client/api/folder_api.py
kameleo/local_api_client/api/general_api.py
kameleo/local_api_client/api/kernel_api.py
kameleo/local_api_client/api/profile_api.py
kameleo/local_api_client/models/__init__.py
kameleo/local_api_client/models/add_profile_to_folder_request.py
kameleo/local_api_client/models/audio_spoofing_type.py
kameleo/local_api_client/models/browser.py
kameleo/local_api_client/models/browser_cookie.py
kameleo/local_api_client/models/browser_settings.py
kameleo/local_api_client/models/canvas_spoofing_type.py
kameleo/local_api_client/models/cookie_request.py
kameleo/local_api_client/models/create_folder_request.py
kameleo/local_api_client/models/create_profile_request.py
kameleo/local_api_client/models/delete_folder_response.py
kameleo/local_api_client/models/device.py
kameleo/local_api_client/models/device_memory_choice.py
kameleo/local_api_client/models/device_memory_spoofing_type.py
kameleo/local_api_client/models/export_profile_request.py
kameleo/local_api_client/models/fingerprint.py
kameleo/local_api_client/models/fingerprint_preview.py
kameleo/local_api_client/models/folder_response.py
kameleo/local_api_client/models/font_spoofing_type.py
kameleo/local_api_client/models/geolocation_choice.py
kameleo/local_api_client/models/geolocation_spoofing_options.py
kameleo/local_api_client/models/geolocation_spoofing_type.py
kameleo/local_api_client/models/group_role.py
kameleo/local_api_client/models/hardware_concurrency_choice.py
kameleo_local_api_client-4.1.0.dist-info/licenses/LICENSE.txt
kameleo_local_api_client-4.1.0.dist-info/METADATA
kameleo_local_api_client-4.1.0.dist-info/WHEEL
kameleo_local_api_client-4.1.0.dist-info/top_level.txt
kameleo_local_api_client-4.1.0.dist-info/RECORD
