Metadata-Version: 2.4
Name: kameleo.local-api-client
Version: 4.1.0
Summary: This Python package provides convenient access to the Local API REST interface of the Kameleo Client.
Home-page: https://github.com/kameleo-io/local-api-client-python
Author: Kameleo Team
Author-email: support@kameleo.io
License: MIT
Keywords: kameleo.local-api-client,kameleo,stealth browsing platform,anti-detect browser,selenium,webdriver,browser automation,web scraping,puppeteer,playwright,headless,chrome,firefox,chromium,edge
Classifier: Programming Language :: Python :: 3
Classifier: License :: OSI Approved :: MIT License
Classifier: Operating System :: OS Independent
License-File: LICENSE.txt
Requires-Dist: urllib3<3.0.0,>=1.25.3
Requires-Dist: python-dateutil>=2.8.2
Requires-Dist: pydantic>=2
Requires-Dist: typing-extensions>=4.7.1
Dynamic: author
Dynamic: author-email
Dynamic: classifier
Dynamic: description
Dynamic: description-content-type
Dynamic: home-page
Dynamic: keywords
Dynamic: license
Dynamic: license-file
Dynamic: requires-dist
Dynamic: summary
